skittles/__init__.py
skittles/api/__init__.py
skittles/api/ob.py
skittles/driver/__init__.py
skittles/driver/http.py
skittles/driver/model.py
skittles/driver/ws.py
skittles/entity/__init__.py
skittles/entity/bot.py
skittles/entity/connection.py
skittles/platform/__init__.py
skittles/platform/mirai.py
skittles/platform/model.py
skittles-0.1.1.dist-info/LICENSE
skittles-0.1.1.dist-info/METADATA
skittles-0.1.1.dist-info/WHEEL
skittles-0.1.1.dist-info/top_level.txt
skittles-0.1.1.dist-info/RECORD
