Metadata-Version: 2.1
Name: skittles
Version: 0.1.1
Summary: mirai-api-http Mock 测试工具
Home-page: https://github.com/RockChinQ/Skittles
Author: RockChinQ
Author-email: 1010553892@qq.com
License: GNU Affero General Public License v3.0
Project-URL: Bug Report, https://github.com/RockChinQ/Skittles/issues
Classifier: License :: OSI Approved :: GNU General Public License v3 (GPLv3)
Classifier: Intended Audience :: Developers
Classifier: Intended Audience :: End Users/Desktop
Classifier: Natural Language :: Chinese (Simplified)
Classifier: Topic :: Software Development :: Libraries :: Python Modules
Classifier: Programming Language :: Python :: 3 :: Only
Classifier: Programming Language :: Python :: 3.6
Classifier: Programming Language :: Python :: 3.7
Classifier: Programming Language :: Python :: 3.8
Classifier: Programming Language :: Python :: 3.9
Classifier: Programming Language :: Python :: 3.10
Classifier: Programming Language :: Python :: 3.11
License-File: LICENSE
Requires-Dist: websockets
Requires-Dist: pydantic
Requires-Dist: quart
Requires-Dist: aiocqhttp
